tradebots/__init__.py
tradebots/interface.py
tradebots/server.py
tradebots/tradebot.py
tradebots-0.5.17.dist-info/METADATA
tradebots-0.5.17.dist-info/WHEEL
tradebots-0.5.17.dist-info/top_level.txt
tradebots-0.5.17.dist-info/RECORD
