Metadata-Version: 2.1
Name: tradebots
Version: 0.5.17
Summary: Package for building tradebots
Home-page: https://github.com/yourusername/your_package
Author: Kryzhanovskiy Maxim
Author-email: kryzhanovskiymax@mail.ru
Classifier: Programming Language :: Python :: 3
Classifier: License :: OSI Approved :: MIT License
Classifier: Operating System :: OS Independent
Requires-Python: >=3.6
Requires-Dist: typing ==3.7.4.3
Requires-Dist: requests ==2.32.3
Requires-Dist: fastapi ==0.112.0
Requires-Dist: httpx ==0.20.0
